__lib/__init__.py
__lib/credentials.py
__lib/endpoints.py
__lib/exceptions.py
__lib/methods.py
endpoints/__init__.py
endpoints/credentials.py
endpoints/endpoints.py
endpoints/exceptions.py
endpoints/lib.py
endpoints/methods.py
endpoints/lib/__init__.py
endpoints/lib/credentials.py
endpoints/lib/endpoints.py
endpoints/lib/exceptions.py
endpoints/lib/methods.py
endpoints_mapper-0.3.1.dist-info/LICENSE
endpoints_mapper-0.3.1.dist-info/METADATA
endpoints_mapper-0.3.1.dist-info/WHEEL
endpoints_mapper-0.3.1.dist-info/top_level.txt
endpoints_mapper-0.3.1.dist-info/RECORD
