Metadata-Version: 2.1
Name: endpoints-mapper
Version: 0.3.1
Summary: ReST API Endpoint Mapper
Home-page: https://gitlab.com/velvetkeyboad/py-endpoints
Author: Ramon Moraes
Author-email: ramonmoraes8080@gmail.com
License: MIT
Platform: UNKNOWN
Classifier: Development Status :: 4 - Beta
Classifier: Intended Audience :: Developers
Classifier: Natural Language :: English
Classifier: License :: OSI Approved :: MIT License
Classifier: Operating System :: POSIX :: Linux
Classifier: Programming Language :: Python
Classifier: Programming Language :: Python :: 3
Classifier: Programming Language :: Python :: 3.6
Classifier: Programming Language :: Python :: 3.7
Classifier: Programming Language :: Python :: 3.8
Classifier: Topic :: Internet :: WWW/HTTP
Classifier: Topic :: Software Development :: Libraries
Requires-Dist: requests (>=2.0.0)
